MANIFEST.in
README.rst
setup.py
bases/__init__.py
bases/admin.py
bases/models.py
bases/tests.py
bases/urls.py
bases/views.py
bases/static/bases/base.js
bases/templates/bases/base.html
bases/templates/bases/base_with_nav.html
djangoapps_lunch.egg-info/PKG-INFO
djangoapps_lunch.egg-info/SOURCES.txt
djangoapps_lunch.egg-info/dependency_links.txt
djangoapps_lunch.egg-info/requires.txt
djangoapps_lunch.egg-info/top_level.txt
lunchapp/__init__.py
lunchapp/admin.py
lunchapp/models.py
lunchapp/serializers.py
lunchapp/tests.py
lunchapp/urls.py
lunchapp/views.py
lunchapp/static/lunchapp/lunch.js
lunchapp/static/lunchapp/ui-bootstrap-tpls-0.14.2.min.js
lunchapp/templates/lunchapp/aaaa.html
lunchapp/templates/lunchapp/account_charge_template.html
lunchapp/templates/lunchapp/all_cashmove_template.html
lunchapp/templates/lunchapp/all_orders_template.html
lunchapp/templates/lunchapp/index.html
lunchapp/templates/lunchapp/my_cashmove.html
lunchapp/templates/lunchapp/my_orders_template.html
lunchapp/templates/lunchapp/order_add_template.html
lunchapp/templates/lunchapp/order_line_operation_template.html
lunchapp/templates/lunchapp/product_add_template.html
lunchapp/templates/lunchapp/product_category_add_template.html
lunchapp/templates/lunchapp/product_category_detail_template.html
lunchapp/templates/lunchapp/product_category_list.html
lunchapp/templates/lunchapp/product_detail_template.html
lunchapp/templates/lunchapp/product_list_template.html
usercenter/__init__.py
usercenter/admin.py
usercenter/models.py
usercenter/tests.py
usercenter/urls.py
usercenter/views.py
usercenter/static/usercenter/usercenter.js
usercenter/templates/usercenter/usercenter_changepwd.html
usercenter/templates/usercenter/usercenter_login.html
usercenter/templates/usercenter/usercenter_register.html